gblackboard/__init__.py
gblackboard/cli.py
gblackboard/data.py
gblackboard/exception.py
gblackboard/gblackboard.py
gblackboard/wrapper.py
gblackboard-0.2.2.dist-info/AUTHORS.rst
gblackboard-0.2.2.dist-info/LICENSE
gblackboard-0.2.2.dist-info/METADATA
gblackboard-0.2.2.dist-info/WHEEL
gblackboard-0.2.2.dist-info/entry_points.txt
gblackboard-0.2.2.dist-info/top_level.txt
gblackboard-0.2.2.dist-info/RECORD
