Metadata-Version: 2.1
Name: gblackboard
Version: 0.2.2
Summary: Blackboard pattern implementation
Home-page: https://github.com/GTedHa/gblackboard
Author: G.Ted
Author-email: gted221@gmail.com
License: MIT license
Keywords: gblackboard
Platform: UNKNOWN
Classifier: Development Status :: 2 - Pre-Alpha
Classifier: Intended Audience :: Developers
Classifier: License :: OSI Approved :: MIT License
Classifier: Natural Language :: English
Classifier: Programming Language :: Python :: 3.4
Classifier: Programming Language :: Python :: 3.5
Classifier: Programming Language :: Python :: 3.6
Classifier: Programming Language :: Python :: 3.7
Requires-Dist: Click (>=6.0)
Requires-Dist: redis (>=3.0.0)
